dynrender_skia-0.2.9.dist-info/METADATA
dynrender_skia-0.2.9.dist-info/WHEEL
dynrender_skia-0.2.9.dist-info/entry_points.txt
dynrender_skia-0.2.9.dist-info/licenses/LICENSE
dynrender_skia/Core.py
dynrender_skia/DynAdditional.py
dynrender_skia/DynConfig.py
dynrender_skia/DynHeader.py
dynrender_skia/DynMajor.py
dynrender_skia/DynRepost.py
dynrender_skia/DynStyle.py
dynrender_skia/DynText.py
dynrender_skia/DynTools.py
dynrender_skia/Static.zip
dynrender_skia/__init__.py
dynrender_skia/exception.py
dynrender_skia-0.2.9.dist-info/RECORD
