Metadata-Version: 2.1
Name: dynrender_skia
Version: 0.2.9
Summary: 使用skia-python将BiliBili动态渲染为图片
Author-Email: DMC <lzxder@outlook.com>, BalconyJH <balconyjh@gmail.com>
License: GNU GPLv3
Requires-Python: <4.0,>=3.9
Requires-Dist: skia-python>=132.0b11
Requires-Dist: httpx<1.0.0,>=0.24.1
Requires-Dist: emoji<3.0.0,>=2.6.0
Requires-Dist: dynamicadaptor<1.0.0,>=0.4.9
Requires-Dist: aiofiles~=23.2
Requires-Dist: tenacity>=8.4.1
